{"1": [{"neg": 0.0, "neu": 1.0, "pos": 0.0, "compound": 0.0}, {"neg": 0.0, "neu": 1.0, "pos": 0.0, "compound": 0.0}, {"neg": 0.0, "neu": 0.963, "pos": 0.037, "compound": 0.2023}, {"neg": 0.0, "neu": 1.0, "pos": 0.0, "compound": 0.0}, {"neg": 0.067, "neu": 0.933, "pos": 0.0, "compound": -0.3818}, {"neg": 0.0, "neu": 0.949, "pos": 0.051, "compound": 0.2263}, {"neg": 0.152, "neu": 0.784, "pos": 0.063, "compound": -0.4451}, {"neg": 0.0, "neu": 0.911, "pos": 0.089, "compound": 0.34}, {"neg": 0.0, "neu": 1.0, "pos": 0.0, "compound": 0.0}, {"neg": 0.0, "neu": 1.0, "pos": 0.0, "compound": 0.0}, {"neg": 0.072, "neu": 0.928, "pos": 0.0, "compound": -0.2732}, {"neg": 0.0, "neu": 0.961, "pos": 0.039, "compound": 0.0129}, {"neg": 0.0, "neu": 0.603, "pos": 0.397, "compound": 0.5574}, {"neg": 0.0, "neu": 1.0, "pos": 0.0, "compound": 0.0}, {"neg": 0.111, "neu": 0.889, "pos": 0.0, "compound": -0.6808}, {"neg": 0.167, "neu": 0.833, "pos": 0.0, "compound": -0.4588}, {"neg": 0.069, "neu": 0.902, "pos": 0.028, "compound": -0.3804}, {"neg": 0.0, "neu": 1.0, "pos": 0.0, "compound": 0.0}, {"neg": 0.0, "neu": 1.0, "pos": 0.0, "compound": 0.0}, {"neg": 0.0, "neu": 1.0, "pos": 0.0, "compound": 0.0}], "0": [{"neg": 0.0, "neu": 1.0, "pos": 0.0, "compound": 0.0}, {"neg": 0.057, "neu": 0.859, "pos": 0.084, "compound": 0.1901}, {"neg": 0.0, "neu": 0.811, "pos": 0.189, "compound": 0.4215}, {"neg": 0.148, "neu": 0.455, "pos": 0.397, "compound": 0.7125}, {"neg": 0.0, "neu": 1.0, "pos": 0.0, "compound": 0.0}, {"neg": 0.0, "neu": 1.0, "pos": 0.0, "compound": 0.0}, {"neg": 0.131, "neu": 0.657, "pos": 0.211, "compound": 0.3254}, {"neg": 0.0, "neu": 1.0, "pos": 0.0, "compound": 0.0}, {"neg": 0.107, "neu": 0.833, "pos": 0.06, "compound": -0.2023}, {"neg": 0.0, "neu": 1.0, "pos": 0.0, "compound": 0.0}, {"neg": 0.044, "neu": 0.956, "pos": 0.0, "compound": -0.296}, {"neg": 0.0, "neu": 1.0, "pos": 0.0, "compound": 0.0}, {"neg": 0.0, "neu": 0.877, "pos": 0.123, "compound": 0.6369}, {"neg": 0.0, "neu": 1.0, "pos": 0.0, "compound": 0.0}, {"neg": 0.115, "neu": 0.713, "pos": 0.171, "compound": 0.2558}, {"neg": 0.0, "neu": 0.0, "pos": 0.0, "compound": 0.0}, {"neg": 0.0, "neu": 0.0, "pos": 0.0, "compound": 0.0}, {"neg": 0.0, "neu": 1.0, "pos": 0.0, "compound": 0.0}, {"neg": 0.0, "neu": 1.0, "pos": 0.0, "compound": 0.0}, {"neg": 0.069, "neu": 0.884, "pos": 0.047, "compound": -0.34}], "all": {"neg": 0.02409375, "neu": 0.8468749999999999, "pos": 0.035234375000000005, "compound": 0.004934375000000003}, "2": [{"neg": 0.0, "neu": 1.0, "pos": 0.0, "compound": 0.0}, {"neg": 0.0, "neu": 0.93, "pos": 0.07, "compound": 0.2732}, {"neg": 0.0, "neu": 1.0, "pos": 0.0, "compound": 0.0}, {"neg": 0.0, "neu": 1.0, "pos": 0.0, "compound": 0.0}, {"neg": 0.0, "neu": 1.0, "pos": 0.0, "compound": 0.0}, {"neg": 0.0, "neu": 0.0, "pos": 0.0, "compound": 0.0}, {"neg": 0.0, "neu": 0.0, "pos": 0.0, "compound": 0.0}, {"neg": 0.0, "neu": 1.0, "pos": 0.0, "compound": 0.0}, {"neg": 0.0, "neu": 0.0, "pos": 0.0, "compound": 0.0}, {"neg": 0.0, "neu": 0.0, "pos": 0.0, "compound": 0.0}, {"neg": 0.0, "neu": 1.0, "pos": 0.0, "compound": 0.0}, {"neg": 0.0, "neu": 0.972, "pos": 0.028, "compound": 0.0772}, {"neg": 0.07, "neu": 0.823, "pos": 0.108, "compound": 0.0516}, {"neg": 0.0, "neu": 1.0, "pos": 0.0, "compound": 0.0}, {"neg": 0.0, "neu": 1.0, "pos": 0.0, "compound": 0.0}, {"neg": 0.112, "neu": 0.888, "pos": 0.0, "compound": -0.6369}, {"neg": 0.051, "neu": 0.886, "pos": 0.063, "compound": 0.128}, {"neg": 0.0, "neu": 1.0, "pos": 0.0, "compound": 0.0}, {"neg": 0.0, "neu": 1.0, "pos": 0.0, "compound": 0.0}, {"neg": 0.0, "neu": 1.0, "pos": 0.0, "compound": 0.0}, {"neg": 0.0, "neu": 1.0, "pos": 0.0, "compound": 0.0}, {"neg": 0.0, "neu": 1.0, "pos": 0.0, "compound": 0.0}, {"neg": 0.0, "neu": 1.0, "pos": 0.0, "compound": 0.0}, {"neg": 0.0, "neu": 1.0, "pos": 0.0, "compound": 0.0}]}