{"all": {"neg": 0.031158536585365843, "neu": 0.916213414634146, "pos": 0.028243902439024388, "compound": -0.01653963414634147}, "1": [{"neg": 0.0, "neu": 1.0, "pos": 0.0, "compound": 0.0}, {"neg": 0.0, "neu": 0.884, "pos": 0.116, "compound": 0.3612}, {"neg": 0.0, "neu": 1.0, "pos": 0.0, "compound": 0.0}, {"neg": 0.0, "neu": 1.0, "pos": 0.0, "compound": 0.0}, {"neg": 0.0, "neu": 1.0, "pos": 0.0, "compound": 0.0}, {"neg": 0.119, "neu": 0.881, "pos": 0.0, "compound": -0.3182}, {"neg": 0.0, "neu": 1.0, "pos": 0.0, "compound": 0.0}, {"neg": 0.0, "neu": 1.0, "pos": 0.0, "compound": 0.0}, {"neg": 0.355, "neu": 0.645, "pos": 0.0, "compound": -0.296}, {"neg": 0.0, "neu": 0.922, "pos": 0.078, "compound": 0.0258}, {"neg": 0.0, "neu": 1.0, "pos": 0.0, "compound": 0.0}, {"neg": 0.09, "neu": 0.675, "pos": 0.236, "compound": 0.381}, {"neg": 0.15, "neu": 0.85, "pos": 0.0, "compound": -0.3182}, {"neg": 0.0, "neu": 1.0, "pos": 0.0, "compound": 0.0}, {"neg": 0.0, "neu": 1.0, "pos": 0.0, "compound": 0.0}, {"neg": 0.0, "neu": 1.0, "pos": 0.0, "compound": 0.0}, {"neg": 0.0, "neu": 1.0, "pos": 0.0, "compound": 0.0}, {"neg": 0.0, "neu": 1.0, "pos": 0.0, "compound": 0.0}, {"neg": 0.0, "neu": 1.0, "pos": 0.0, "compound": 0.0}, {"neg": 0.0, "neu": 1.0, "pos": 0.0, "compound": 0.0}, {"neg": 0.0, "neu": 1.0, "pos": 0.0, "compound": 0.0}, {"neg": 0.0, "neu": 1.0, "pos": 0.0, "compound": 0.0}, {"neg": 0.0, "neu": 0.815, "pos": 0.185, "compound": 0.1511}, {"neg": 0.0, "neu": 1.0, "pos": 0.0, "compound": 0.0}, {"neg": 0.0, "neu": 1.0, "pos": 0.0, "compound": 0.0}, {"neg": 0.103, "neu": 0.897, "pos": 0.0, "compound": -0.4939}, {"neg": 0.0, "neu": 1.0, "pos": 0.0, "compound": 0.0}, {"neg": 0.122, "neu": 0.878, "pos": 0.0, "compound": -0.3612}, {"neg": 0.0, "neu": 1.0, "pos": 0.0, "compound": 0.0}], "0": [{"neg": 0.0, "neu": 0.718, "pos": 0.282, "compound": 0.8345}, {"neg": 0.101, "neu": 0.736, "pos": 0.163, "compound": 0.3254}, {"neg": 0.0, "neu": 1.0, "pos": 0.0, "compound": 0.0}, {"neg": 0.0, "neu": 1.0, "pos": 0.0, "compound": 0.0}, {"neg": 0.127, "neu": 0.873, "pos": 0.0, "compound": -0.4939}, {"neg": 0.0, "neu": 1.0, "pos": 0.0, "compound": 0.0}, {"neg": 0.0, "neu": 1.0, "pos": 0.0, "compound": 0.0}, {"neg": 0.0, "neu": 1.0, "pos": 0.0, "compound": 0.0}, {"neg": 0.0, "neu": 1.0, "pos": 0.0, "compound": 0.0}, {"neg": 0.0, "neu": 1.0, "pos": 0.0, "compound": 0.0}, {"neg": 0.0, "neu": 1.0, "pos": 0.0, "compound": 0.0}, {"neg": 0.067, "neu": 0.933, "pos": 0.0, "compound": -0.128}, {"neg": 0.0, "neu": 1.0, "pos": 0.0, "compound": 0.0}, {"neg": 0.0, "neu": 1.0, "pos": 0.0, "compound": 0.0}, {"neg": 0.0, "neu": 1.0, "pos": 0.0, "compound": 0.0}, {"neg": 0.0, "neu": 1.0, "pos": 0.0, "compound": 0.0}, {"neg": 0.0, "neu": 1.0, "pos": 0.0, "compound": 0.0}, {"neg": 0.0, "neu": 1.0, "pos": 0.0, "compound": 0.0}, {"neg": 0.0, "neu": 1.0, "pos": 0.0, "compound": 0.0}, {"neg": 0.0, "neu": 1.0, "pos": 0.0, "compound": 0.0}, {"neg": 0.0, "neu": 1.0, "pos": 0.0, "compound": 0.0}, {"neg": 0.0, "neu": 1.0, "pos": 0.0, "compound": 0.0}, {"neg": 0.0, "neu": 1.0, "pos": 0.0, "compound": 0.0}, {"neg": 0.0, "neu": 1.0, "pos": 0.0, "compound": 0.0}, {"neg": 0.145, "neu": 0.855, "pos": 0.0, "compound": -0.296}, {"neg": 0.0, "neu": 1.0, "pos": 0.0, "compound": 0.0}], "3": [{"neg": 0.11, "neu": 0.803, "pos": 0.087, "compound": -0.1779}, {"neg": 0.0, "neu": 1.0, "pos": 0.0, "compound": 0.0}, {"neg": 0.0, "neu": 1.0, "pos": 0.0, "compound": 0.0}, {"neg": 0.0, "neu": 1.0, "pos": 0.0, "compound": 0.0}, {"neg": 0.319, "neu": 0.6, "pos": 0.08, "compound": -0.8674}, {"neg": 0.037, "neu": 0.907, "pos": 0.056, "compound": 0.223}, {"neg": 0.111, "neu": 0.788, "pos": 0.101, "compound": -0.128}, {"neg": 0.0, "neu": 1.0, "pos": 0.0, "compound": 0.0}, {"neg": 0.0, "neu": 1.0, "pos": 0.0, "compound": 0.0}, {"neg": 0.0, "neu": 1.0, "pos": 0.0, "compound": 0.0}, {"neg": 0.0, "neu": 1.0, "pos": 0.0, "compound": 0.0}, {"neg": 0.0, "neu": 1.0, "pos": 0.0, "compound": 0.0}, {"neg": 0.0, "neu": 1.0, "pos": 0.0, "compound": 0.0}, {"neg": 0.0, "neu": 1.0, "pos": 0.0, "compound": 0.0}, {"neg": 0.043, "neu": 0.957, "pos": 0.0, "compound": -0.296}, {"neg": 0.0, "neu": 1.0, "pos": 0.0, "compound": 0.0}, {"neg": 0.0, "neu": 1.0, "pos": 0.0, "compound": 0.0}, {"neg": 0.281, "neu": 0.496, "pos": 0.223, "compound": -0.1779}], "2": [{"neg": 0.13, "neu": 0.87, "pos": 0.0, "compound": -0.2023}, {"neg": 0.0, "neu": 1.0, "pos": 0.0, "compound": 0.0}, {"neg": 0.0, "neu": 1.0, "pos": 0.0, "compound": 0.0}, {"neg": 0.0, "neu": 1.0, "pos": 0.0, "compound": 0.0}, {"neg": 0.0, "neu": 1.0, "pos": 0.0, "compound": 0.0}, {"neg": 0.08, "neu": 0.799, "pos": 0.121, "compound": 0.0772}, {"neg": 0.209, "neu": 0.791, "pos": 0.0, "compound": -0.4404}, {"neg": 0.0, "neu": 1.0, "pos": 0.0, "compound": 0.0}, {"neg": 0.0, "neu": 1.0, "pos": 0.0, "compound": 0.0}, {"neg": 0.0, "neu": 1.0, "pos": 0.0, "compound": 0.0}, {"neg": 0.102, "neu": 0.898, "pos": 0.0, "compound": -0.3818}, {"neg": 0.0, "neu": 1.0, "pos": 0.0, "compound": 0.0}, {"neg": 0.0, "neu": 0.789, "pos": 0.211, "compound": 0.1531}, {"neg": 0.0, "neu": 1.0, "pos": 0.0, "compound": 0.0}, {"neg": 0.082, "neu": 0.892, "pos": 0.027, "compound": -0.5106}, {"neg": 0.0, "neu": 1.0, "pos": 0.0, "compound": 0.0}, {"neg": 0.218, "neu": 0.669, "pos": 0.113, "compound": -0.3641}, {"neg": 0.0, "neu": 1.0, "pos": 0.0, "compound": 0.0}, {"neg": 0.0, "neu": 0.868, "pos": 0.132, "compound": 0.296}, {"neg": 0.082, "neu": 0.681, "pos": 0.236, "compound": 0.5245}, {"neg": 0.139, "neu": 0.723, "pos": 0.139, "compound": 0.0}, {"neg": 0.0, "neu": 1.0, "pos": 0.0, "compound": 0.0}, {"neg": 0.0, "neu": 0.426, "pos": 0.574, "compound": 0.4019}], "5": [{"neg": 0.0, "neu": 1.0, "pos": 0.0, "compound": 0.0}, {"neg": 0.0, "neu": 1.0, "pos": 0.0, "compound": 0.0}, {"neg": 0.0, "neu": 1.0, "pos": 0.0, "compound": 0.0}, {"neg": 0.0, "neu": 1.0, "pos": 0.0, "compound": 0.0}, {"neg": 0.105, "neu": 0.895, "pos": 0.0, "compound": -0.5106}, {"neg": 0.0, "neu": 0.877, "pos": 0.123, "compound": 0.4215}, {"neg": 0.0, "neu": 1.0, "pos": 0.0, "compound": 0.0}, {"neg": 0.0, "neu": 1.0, "pos": 0.0, "compound": 0.0}, {"neg": 0.0, "neu": 1.0, "pos": 0.0, "compound": 0.0}, {"neg": 0.104, "neu": 0.787, "pos": 0.109, "compound": 0.033}, {"neg": 0.0, "neu": 1.0, "pos": 0.0, "compound": 0.0}, {"neg": 0.537, "neu": 0.463, "pos": 0.0, "compound": -0.7003}, {"neg": 0.0, "neu": 1.0, "pos": 0.0, "compound": 0.0}, {"neg": 0.0, "neu": 1.0, "pos": 0.0, "compound": 0.0}, {"neg": 0.0, "neu": 0.919, "pos": 0.081, "compound": 0.3875}, {"neg": 0.0, "neu": 1.0, "pos": 0.0, "compound": 0.0}, {"neg": 0.0, "neu": 0.899, "pos": 0.101, "compound": 0.4215}, {"neg": 0.0, "neu": 1.0, "pos": 0.0, "compound": 0.0}, {"neg": 0.0, "neu": 1.0, "pos": 0.0, "compound": 0.0}, {"neg": 0.0, "neu": 0.963, "pos": 0.037, "compound": 0.0258}, {"neg": 0.0, "neu": 1.0, "pos": 0.0, "compound": 0.0}, {"neg": 0.0, "neu": 1.0, "pos": 0.0, "compound": 0.0}, {"neg": 0.0, "neu": 0.843, "pos": 0.157, "compound": 0.4215}, {"neg": 0.0, "neu": 0.0, "pos": 0.0, "compound": 0.0}, {"neg": 0.0, "neu": 0.0, "pos": 0.0, "compound": 0.0}, {"neg": 0.0, "neu": 1.0, "pos": 0.0, "compound": 0.0}, {"neg": 0.0, "neu": 1.0, "pos": 0.0, "compound": 0.0}], "4": [{"neg": 0.0, "neu": 1.0, "pos": 0.0, "compound": 0.0}, {"neg": 0.0, "neu": 1.0, "pos": 0.0, "compound": 0.0}, {"neg": 0.0, "neu": 0.863, "pos": 0.137, "compound": 0.4019}, {"neg": 0.0, "neu": 1.0, "pos": 0.0, "compound": 0.0}, {"neg": 0.153, "neu": 0.847, "pos": 0.0, "compound": -0.4881}, {"neg": 0.0, "neu": 1.0, "pos": 0.0, "compound": 0.0}, {"neg": 0.0, "neu": 1.0, "pos": 0.0, "compound": 0.0}, {"neg": 0.095, "neu": 0.905, "pos": 0.0, "compound": -0.25}, {"neg": 0.0, "neu": 1.0, "pos": 0.0, "compound": 0.0}, {"neg": 0.081, "neu": 0.919, "pos": 0.0, "compound": -0.296}, {"neg": 0.0, "neu": 1.0, "pos": 0.0, "compound": 0.0}, {"neg": 0.0, "neu": 1.0, "pos": 0.0, "compound": 0.0}, {"neg": 0.0, "neu": 1.0, "pos": 0.0, "compound": 0.0}, {"neg": 0.0, "neu": 1.0, "pos": 0.0, "compound": 0.0}, {"neg": 0.0, "neu": 1.0, "pos": 0.0, "compound": 0.0}, {"neg": 0.114, "neu": 0.743, "pos": 0.143, "compound": 0.128}, {"neg": 0.0, "neu": 1.0, "pos": 0.0, "compound": 0.0}, {"neg": 0.0, "neu": 1.0, "pos": 0.0, "compound": 0.0}, {"neg": 0.0, "neu": 1.0, "pos": 0.0, "compound": 0.0}, {"neg": 0.0, "neu": 0.0, "pos": 0.0, "compound": 0.0}, {"neg": 0.0, "neu": 0.0, "pos": 0.0, "compound": 0.0}, {"neg": 0.082, "neu": 0.918, "pos": 0.0, "compound": -0.3818}, {"neg": 0.0, "neu": 1.0, "pos": 0.0, "compound": 0.0}, {"neg": 0.0, "neu": 1.0, "pos": 0.0, "compound": 0.0}], "7": [{"neg": 0.0, "neu": 0.909, "pos": 0.091, "compound": 0.4215}, {"neg": 0.0, "neu": 1.0, "pos": 0.0, "compound": 0.0}], "6": [{"neg": 0.0, "neu": 1.0, "pos": 0.0, "compound": 0.0}, {"neg": 0.0, "neu": 1.0, "pos": 0.0, "compound": 0.0}, {"neg": 0.237, "neu": 0.763, "pos": 0.0, "compound": -0.7096}, {"neg": 0.172, "neu": 0.828, "pos": 0.0, "compound": -0.7003}, {"neg": 0.0, "neu": 1.0, "pos": 0.0, "compound": 0.0}, {"neg": 0.0, "neu": 0.976, "pos": 0.024, "compound": 0.0258}, {"neg": 0.0, "neu": 1.0, "pos": 0.0, "compound": 0.0}, {"neg": 0.0, "neu": 0.921, "pos": 0.079, "compound": 0.6486}, {"neg": 0.0, "neu": 1.0, "pos": 0.0, "compound": 0.0}, {"neg": 0.0, "neu": 1.0, "pos": 0.0, "compound": 0.0}, {"neg": 0.0, "neu": 1.0, "pos": 0.0, "compound": 0.0}, {"neg": 0.0, "neu": 0.896, "pos": 0.104, "compound": 0.4404}, {"neg": 0.108, "neu": 0.892, "pos": 0.0, "compound": -0.2057}, {"neg": 0.0, "neu": 0.714, "pos": 0.286, "compound": 0.25}, {"neg": 0.0, "neu": 1.0, "pos": 0.0, "compound": 0.0}]}