{"1": [{"neg": 0.068, "neu": 0.778, "pos": 0.154, "compound": 0.7096}, {"neg": 0.0, "neu": 1.0, "pos": 0.0, "compound": 0.0}, {"neg": 0.068, "neu": 0.821, "pos": 0.111, "compound": 0.296}, {"neg": 0.0, "neu": 1.0, "pos": 0.0, "compound": 0.0}, {"neg": 0.0, "neu": 1.0, "pos": 0.0, "compound": 0.0}, {"neg": 0.076, "neu": 0.924, "pos": 0.0, "compound": -0.2411}, {"neg": 0.0, "neu": 1.0, "pos": 0.0, "compound": 0.0}, {"neg": 0.0, "neu": 1.0, "pos": 0.0, "compound": 0.0}, {"neg": 0.066, "neu": 0.778, "pos": 0.156, "compound": 0.25}, {"neg": 0.0, "neu": 1.0, "pos": 0.0, "compound": 0.0}, {"neg": 0.108, "neu": 0.892, "pos": 0.0, "compound": -0.5423}, {"neg": 0.0, "neu": 1.0, "pos": 0.0, "compound": 0.0}, {"neg": 0.0, "neu": 0.0, "pos": 0.0, "compound": 0.0}, {"neg": 0.0, "neu": 0.0, "pos": 0.0, "compound": 0.0}, {"neg": 0.0, "neu": 0.149, "pos": 0.851, "compound": 0.6908}, {"neg": 0.0, "neu": 1.0, "pos": 0.0, "compound": 0.0}, {"neg": 0.0, "neu": 1.0, "pos": 0.0, "compound": 0.0}, {"neg": 0.0, "neu": 1.0, "pos": 0.0, "compound": 0.0}, {"neg": 0.0, "neu": 0.701, "pos": 0.299, "compound": 0.7709}, {"neg": 0.0, "neu": 1.0, "pos": 0.0, "compound": 0.0}, {"neg": 0.0, "neu": 1.0, "pos": 0.0, "compound": 0.0}, {"neg": 0.0, "neu": 1.0, "pos": 0.0, "compound": 0.0}, {"neg": 0.0, "neu": 1.0, "pos": 0.0, "compound": 0.0}, {"neg": 0.0, "neu": 1.0, "pos": 0.0, "compound": 0.0}, {"neg": 0.119, "neu": 0.813, "pos": 0.068, "compound": -0.3182}, {"neg": 0.0, "neu": 1.0, "pos": 0.0, "compound": 0.0}, {"neg": 0.0, "neu": 0.588, "pos": 0.412, "compound": 0.4215}, {"neg": 0.0, "neu": 1.0, "pos": 0.0, "compound": 0.0}, {"neg": 0.054, "neu": 0.857, "pos": 0.089, "compound": 0.296}, {"neg": 0.0, "neu": 1.0, "pos": 0.0, "compound": 0.0}, {"neg": 0.0, "neu": 0.0, "pos": 0.0, "compound": 0.0}, {"neg": 0.0, "neu": 0.0, "pos": 0.0, "compound": 0.0}, {"neg": 0.0, "neu": 1.0, "pos": 0.0, "compound": 0.0}, {"neg": 0.0, "neu": 0.0, "pos": 0.0, "compound": 0.0}, {"neg": 0.0, "neu": 0.0, "pos": 0.0, "compound": 0.0}, {"neg": 0.0, "neu": 1.0, "pos": 0.0, "compound": 0.0}, {"neg": 0.0, "neu": 1.0, "pos": 0.0, "compound": 0.0}, {"neg": 0.0, "neu": 1.0, "pos": 0.0, "compound": 0.0}, {"neg": 0.312, "neu": 0.47, "pos": 0.218, "compound": -0.296}, {"neg": 0.0, "neu": 1.0, "pos": 0.0, "compound": 0.0}, {"neg": 0.0, "neu": 1.0, "pos": 0.0, "compound": 0.0}, {"neg": 0.0, "neu": 0.856, "pos": 0.144, "compound": 0.4019}, {"neg": 0.0, "neu": 0.902, "pos": 0.098, "compound": 0.3612}], "0": [{"neg": 0.0, "neu": 1.0, "pos": 0.0, "compound": 0.0}, {"neg": 0.057, "neu": 0.859, "pos": 0.084, "compound": 0.1901}, {"neg": 0.0, "neu": 0.811, "pos": 0.189, "compound": 0.4215}, {"neg": 0.0, "neu": 0.761, "pos": 0.239, "compound": 0.8345}, {"neg": 0.131, "neu": 0.657, "pos": 0.211, "compound": 0.3254}, {"neg": 0.0, "neu": 1.0, "pos": 0.0, "compound": 0.0}, {"neg": 0.123, "neu": 0.75, "pos": 0.127, "compound": 0.0516}, {"neg": 0.0, "neu": 0.89, "pos": 0.11, "compound": 0.3818}, {"neg": 0.0, "neu": 1.0, "pos": 0.0, "compound": 0.0}, {"neg": 0.0, "neu": 0.867, "pos": 0.133, "compound": 0.6705}, {"neg": 0.0, "neu": 0.898, "pos": 0.102, "compound": 0.6908}, {"neg": 0.0, "neu": 1.0, "pos": 0.0, "compound": 0.0}, {"neg": 0.138, "neu": 0.563, "pos": 0.3, "compound": 0.3818}, {"neg": 0.07, "neu": 0.93, "pos": 0.0, "compound": -0.5267}, {"neg": 0.0, "neu": 1.0, "pos": 0.0, "compound": 0.0}], "all": {"neg": 0.024378378378378383, "neu": 0.8305270270270271, "pos": 0.06401351351351352, "compound": 0.09412702702702704}, "2": [{"neg": 0.0, "neu": 1.0, "pos": 0.0, "compound": 0.0}, {"neg": 0.0, "neu": 1.0, "pos": 0.0, "compound": 0.0}, {"neg": 0.0, "neu": 0.787, "pos": 0.213, "compound": 0.4019}, {"neg": 0.123, "neu": 0.82, "pos": 0.057, "compound": -0.3952}, {"neg": 0.0, "neu": 1.0, "pos": 0.0, "compound": 0.0}, {"neg": 0.0, "neu": 1.0, "pos": 0.0, "compound": 0.0}, {"neg": 0.136, "neu": 0.864, "pos": 0.0, "compound": -0.296}, {"neg": 0.0, "neu": 0.899, "pos": 0.101, "compound": 0.5574}, {"neg": 0.0, "neu": 0.729, "pos": 0.271, "compound": 0.7717}, {"neg": 0.0, "neu": 1.0, "pos": 0.0, "compound": 0.0}, {"neg": 0.0, "neu": 1.0, "pos": 0.0, "compound": 0.0}, {"neg": 0.0, "neu": 1.0, "pos": 0.0, "compound": 0.0}, {"neg": 0.0, "neu": 1.0, "pos": 0.0, "compound": 0.0}, {"neg": 0.0, "neu": 1.0, "pos": 0.0, "compound": 0.0}, {"neg": 0.0, "neu": 1.0, "pos": 0.0, "compound": 0.0}, {"neg": 0.155, "neu": 0.845, "pos": 0.0, "compound": -0.296}]}