{"1": [{"neg": 0.0, "neu": 1.0, "pos": 0.0, "compound": 0.0}, {"neg": 0.159, "neu": 0.841, "pos": 0.0, "compound": -0.5267}, {"neg": 0.0, "neu": 1.0, "pos": 0.0, "compound": 0.0}, {"neg": 0.0, "neu": 1.0, "pos": 0.0, "compound": 0.0}, {"neg": 0.076, "neu": 0.924, "pos": 0.0, "compound": -0.6808}, {"neg": 0.0, "neu": 0.9, "pos": 0.1, "compound": 0.2732}, {"neg": 0.0, "neu": 0.0, "pos": 0.0, "compound": 0.0}, {"neg": 0.0, "neu": 0.0, "pos": 0.0, "compound": 0.0}, {"neg": 0.0, "neu": 1.0, "pos": 0.0, "compound": 0.0}, {"neg": 0.0, "neu": 1.0, "pos": 0.0, "compound": 0.0}, {"neg": 0.297, "neu": 0.57, "pos": 0.133, "compound": -0.3818}, {"neg": 0.0, "neu": 1.0, "pos": 0.0, "compound": 0.0}, {"neg": 0.0, "neu": 1.0, "pos": 0.0, "compound": 0.0}, {"neg": 0.0, "neu": 1.0, "pos": 0.0, "compound": 0.0}, {"neg": 0.0, "neu": 1.0, "pos": 0.0, "compound": 0.0}, {"neg": 0.086, "neu": 0.914, "pos": 0.0, "compound": -0.5267}, {"neg": 0.087, "neu": 0.84, "pos": 0.073, "compound": -0.128}, {"neg": 0.0, "neu": 1.0, "pos": 0.0, "compound": 0.0}, {"neg": 0.0, "neu": 1.0, "pos": 0.0, "compound": 0.0}, {"neg": 0.0, "neu": 1.0, "pos": 0.0, "compound": 0.0}, {"neg": 0.166, "neu": 0.834, "pos": 0.0, "compound": -0.6782}, {"neg": 0.0, "neu": 1.0, "pos": 0.0, "compound": 0.0}, {"neg": 0.195, "neu": 0.763, "pos": 0.042, "compound": -0.7003}, {"neg": 0.0, "neu": 1.0, "pos": 0.0, "compound": 0.0}, {"neg": 0.091, "neu": 0.909, "pos": 0.0, "compound": -0.2944}, {"neg": 0.086, "neu": 0.783, "pos": 0.131, "compound": 0.2023}, {"neg": 0.0, "neu": 0.76, "pos": 0.24, "compound": 0.7184}], "0": [{"neg": 0.0, "neu": 1.0, "pos": 0.0, "compound": 0.0}, {"neg": 0.057, "neu": 0.859, "pos": 0.084, "compound": 0.1901}, {"neg": 0.0, "neu": 0.811, "pos": 0.189, "compound": 0.4215}, {"neg": 0.059, "neu": 0.638, "pos": 0.303, "compound": 0.8806}, {"neg": 0.0, "neu": 1.0, "pos": 0.0, "compound": 0.0}, {"neg": 0.201, "neu": 0.767, "pos": 0.032, "compound": -0.91}, {"neg": 0.468, "neu": 0.532, "pos": 0.0, "compound": -0.5267}, {"neg": 0.033, "neu": 0.908, "pos": 0.059, "compound": 0.3818}, {"neg": 0.153, "neu": 0.847, "pos": 0.0, "compound": -0.4404}, {"neg": 0.032, "neu": 0.968, "pos": 0.0, "compound": -0.3182}, {"neg": 0.1, "neu": 0.9, "pos": 0.0, "compound": -0.7962}, {"neg": 0.0, "neu": 1.0, "pos": 0.0, "compound": 0.0}], "all": {"neg": 0.05458181818181818, "neu": 0.8730181818181819, "pos": 0.036, "compound": -0.08064545454545453}, "2": [{"neg": 0.274, "neu": 0.726, "pos": 0.0, "compound": -0.5267}, {"neg": 0.076, "neu": 0.825, "pos": 0.099, "compound": 0.1779}, {"neg": 0.191, "neu": 0.638, "pos": 0.17, "compound": -0.3818}, {"neg": 0.115, "neu": 0.851, "pos": 0.033, "compound": -0.5994}, {"neg": 0.0, "neu": 1.0, "pos": 0.0, "compound": 0.0}, {"neg": 0.0, "neu": 1.0, "pos": 0.0, "compound": 0.0}, {"neg": 0.0, "neu": 1.0, "pos": 0.0, "compound": 0.0}, {"neg": 0.0, "neu": 1.0, "pos": 0.0, "compound": 0.0}, {"neg": 0.0, "neu": 0.897, "pos": 0.103, "compound": 0.2411}, {"neg": 0.0, "neu": 1.0, "pos": 0.0, "compound": 0.0}, {"neg": 0.0, "neu": 0.811, "pos": 0.189, "compound": 0.4939}, {"neg": 0.0, "neu": 1.0, "pos": 0.0, "compound": 0.0}, {"neg": 0.0, "neu": 1.0, "pos": 0.0, "compound": 0.0}, {"neg": 0.0, "neu": 1.0, "pos": 0.0, "compound": 0.0}, {"neg": 0.0, "neu": 1.0, "pos": 0.0, "compound": 0.0}, {"neg": 0.0, "neu": 1.0, "pos": 0.0, "compound": 0.0}]}