{"1": [{"neg": 0.0, "neu": 1.0, "pos": 0.0, "compound": 0.0}, {"neg": 0.0, "neu": 1.0, "pos": 0.0, "compound": 0.0}, {"neg": 0.0, "neu": 1.0, "pos": 0.0, "compound": 0.0}, {"neg": 0.0, "neu": 1.0, "pos": 0.0, "compound": 0.0}, {"neg": 0.06, "neu": 0.94, "pos": 0.0, "compound": -0.3818}, {"neg": 0.0, "neu": 1.0, "pos": 0.0, "compound": 0.0}, {"neg": 0.046, "neu": 0.89, "pos": 0.064, "compound": 0.1935}, {"neg": 0.068, "neu": 0.932, "pos": 0.0, "compound": -0.296}, {"neg": 0.0, "neu": 1.0, "pos": 0.0, "compound": 0.0}, {"neg": 0.0, "neu": 0.923, "pos": 0.077, "compound": 0.4767}, {"neg": 0.0, "neu": 0.895, "pos": 0.105, "compound": 0.4019}, {"neg": 0.231, "neu": 0.769, "pos": 0.0, "compound": -0.4019}, {"neg": 0.065, "neu": 0.935, "pos": 0.0, "compound": -0.1695}, {"neg": 0.0, "neu": 1.0, "pos": 0.0, "compound": 0.0}, {"neg": 0.107, "neu": 0.749, "pos": 0.144, "compound": 0.2023}, {"neg": 0.0, "neu": 1.0, "pos": 0.0, "compound": 0.0}, {"neg": 0.183, "neu": 0.705, "pos": 0.112, "compound": -0.4939}, {"neg": 0.0, "neu": 1.0, "pos": 0.0, "compound": 0.0}, {"neg": 0.0, "neu": 1.0, "pos": 0.0, "compound": 0.0}, {"neg": 0.0, "neu": 1.0, "pos": 0.0, "compound": 0.0}, {"neg": 0.0, "neu": 0.924, "pos": 0.076, "compound": 0.4019}, {"neg": 0.0, "neu": 1.0, "pos": 0.0, "compound": 0.0}, {"neg": 0.0, "neu": 1.0, "pos": 0.0, "compound": 0.0}, {"neg": 0.0, "neu": 1.0, "pos": 0.0, "compound": 0.0}, {"neg": 0.0, "neu": 1.0, "pos": 0.0, "compound": 0.0}, {"neg": 0.0, "neu": 1.0, "pos": 0.0, "compound": 0.0}], "0": [{"neg": 0.0, "neu": 1.0, "pos": 0.0, "compound": 0.0}, {"neg": 0.057, "neu": 0.859, "pos": 0.084, "compound": 0.1901}, {"neg": 0.0, "neu": 0.811, "pos": 0.189, "compound": 0.4215}, {"neg": 0.067, "neu": 0.583, "pos": 0.35, "compound": 0.8806}, {"neg": 0.0, "neu": 1.0, "pos": 0.0, "compound": 0.0}, {"neg": 0.065, "neu": 0.855, "pos": 0.08, "compound": 0.1531}, {"neg": 0.0, "neu": 1.0, "pos": 0.0, "compound": 0.0}, {"neg": 0.0, "neu": 0.807, "pos": 0.193, "compound": 0.4767}, {"neg": 0.265, "neu": 0.594, "pos": 0.142, "compound": -0.4019}, {"neg": 0.0, "neu": 1.0, "pos": 0.0, "compound": 0.0}, {"neg": 0.111, "neu": 0.889, "pos": 0.0, "compound": -0.3612}, {"neg": 0.0, "neu": 0.902, "pos": 0.098, "compound": 0.5574}, {"neg": 0.0, "neu": 1.0, "pos": 0.0, "compound": 0.0}, {"neg": 0.0, "neu": 1.0, "pos": 0.0, "compound": 0.0}, {"neg": 0.0, "neu": 1.0, "pos": 0.0, "compound": 0.0}, {"neg": 0.0, "neu": 1.0, "pos": 0.0, "compound": 0.0}, {"neg": 0.0, "neu": 1.0, "pos": 0.0, "compound": 0.0}, {"neg": 0.0, "neu": 1.0, "pos": 0.0, "compound": 0.0}, {"neg": 0.0, "neu": 1.0, "pos": 0.0, "compound": 0.0}, {"neg": 0.0, "neu": 1.0, "pos": 0.0, "compound": 0.0}, {"neg": 0.0, "neu": 0.918, "pos": 0.082, "compound": 0.1779}, {"neg": 0.0, "neu": 1.0, "pos": 0.0, "compound": 0.0}, {"neg": 0.231, "neu": 0.769, "pos": 0.0, "compound": -0.7184}, {"neg": 0.407, "neu": 0.593, "pos": 0.0, "compound": -0.6705}], "all": {"neg": 0.03926, "neu": 0.9248400000000001, "pos": 0.03592000000000001, "compound": 0.012770000000000012}}